illallangi/tripit/__init__.py
illallangi/tripit/__version__.py
illallangi/tripit/tools.py
illallangi/tripit/utils.py
illallangi/tripit/adapters/__init__.py
illallangi/tripit/adapters/air_transport.py
illallangi/tripit/client/__init__.py
illallangi/tripit/client/flight.py
illallangi/tripit/client/profile.py
illallangi/tripit/client/trip.py
illallangi/tripit/diffsyncmodels/__init__.py
illallangi/tripit/diffsyncmodels/flight.py
illallangi/tripit/diffsyncmodels/trip.py
illallangi/tripit/models/__init__.py
illallangi/tripit/models/flight.py
illallangi/tripit/models/profile.py
illallangi/tripit/models/trip.py
illallangi_tripit-0.8.0.dist-info/METADATA
illallangi_tripit-0.8.0.dist-info/WHEEL
illallangi_tripit-0.8.0.dist-info/entry_points.txt
illallangi_tripit-0.8.0.dist-info/licenses/LICENSE
illallangi_tripit-0.8.0.dist-info/RECORD
